Metadata-Version: 1.0
Name: pythonTdexApi
Version: 0.1
Summary: python-tdex-api
Home-page: https://github.com/tdex-exchange/python-tdex-api
Author: lamsam
Author-email: sam_yulam@163.com
License: MIT
Platform: UNKNOWN
